kr/__init__.py
kr-0.0.5.dist-info/licenses/LICENSE
kr-0.0.5.dist-info/METADATA
kr-0.0.5.dist-info/WHEEL
kr-0.0.5.dist-info/top_level.txt
kr-0.0.5.dist-info/RECORD
